LICENSE.md
README.md
setup.py
rlcard/__init__.py
rlcard/agents/__init__.py
rlcard/agents/cfr_agent.py
rlcard/agents/dqn_agent.py
rlcard/agents/nfsp_agent.py
rlcard/agents/pettingzoo_agents.py
rlcard/agents/random_agent.py
rlcard/agents/dmc_agent/__init__.py
rlcard/agents/dmc_agent/file_writer.py
rlcard/agents/dmc_agent/model.py
rlcard/agents/dmc_agent/pettingzoo_model.py
rlcard/agents/dmc_agent/pettingzoo_utils.py
rlcard/agents/dmc_agent/trainer.py
rlcard/agents/dmc_agent/utils.py
rlcard/agents/human_agents/__init__.py
rlcard/agents/human_agents/blackjack_human_agent.py
rlcard/agents/human_agents/leduc_holdem_human_agent.py
rlcard/agents/human_agents/limit_holdem_human_agent.py
rlcard/agents/human_agents/nolimit_holdem_human_agent.py
rlcard/agents/human_agents/uno_human_agent.py
rlcard/agents/human_agents/gin_rummy_human_agent/__init__.py
rlcard/agents/human_agents/gin_rummy_human_agent/gin_rummy_human_agent.py
rlcard/agents/human_agents/gin_rummy_human_agent/gui_cards/__init__.py
rlcard/agents/human_agents/gin_rummy_human_agent/gui_cards/card_image.py
rlcard/agents/human_agents/gin_rummy_human_agent/gui_gin_rummy/__init__.py
rlcard/agents/human_agents/gin_rummy_human_agent/gui_gin_rummy/canvas_item.py
rlcard/agents/human_agents/gin_rummy_human_agent/gui_gin_rummy/configurations.py
rlcard/agents/human_agents/gin_rummy_human_agent/gui_gin_rummy/env_thread.py
rlcard/agents/human_agents/gin_rummy_human_agent/gui_gin_rummy/game_app.py
rlcard/agents/human_agents/gin_rummy_human_agent/gui_gin_rummy/game_canvas.py
rlcard/agents/human_agents/gin_rummy_human_agent/gui_gin_rummy/game_canvas_debug.py
rlcard/agents/human_agents/gin_rummy_human_agent/gui_gin_rummy/game_canvas_getter.py
rlcard/agents/human_agents/gin_rummy_human_agent/gui_gin_rummy/game_canvas_post_doing_action.py
rlcard/agents/human_agents/gin_rummy_human_agent/gui_gin_rummy/game_canvas_query.py
rlcard/agents/human_agents/gin_rummy_human_agent/gui_gin_rummy/game_canvas_updater.py
rlcard_uno.egg-info/PKG-INFO
rlcard_uno.egg-info/SOURCES.txt
rlcard_uno.egg-info/dependency_links.txt
rlcard_uno.egg-info/requires.txt
rlcard_uno.egg-info/top_level.txt
